setup.py
ledgerman/__init__.py
ledgerman.egg-info/PKG-INFO
ledgerman.egg-info/SOURCES.txt
ledgerman.egg-info/dependency_links.txt
ledgerman.egg-info/entry_points.txt
ledgerman.egg-info/not-zip-safe
ledgerman.egg-info/requires.txt
ledgerman.egg-info/top_level.txt
ledgerman/core/__init__.py
ledgerman/core/account.py
ledgerman/core/exchange.py
ledgerman/core/exchange_rate.py
ledgerman/core/exchange_rate_fetcher.py
ledgerman/core/journal.py
ledgerman/core/money.py
ledgerman/gnc/__init__.py
ledgerman/gnc/gnucash.py
ledgerman/model/__init__.py
ledgerman/model/trade.py
ledgerman/model/trade_account.py
ledgerman/tests/__init__.py
ledgerman/tests/core/__init__.py
ledgerman/tests/core/account.py
ledgerman/tests/core/exchange.py
ledgerman/tests/core/exchange_rate.py
ledgerman/tests/core/exchange_rate_fetcher.py
ledgerman/tests/core/journal.py
ledgerman/tests/core/money.py
ledgerman/tools/__init__.py
ledgerman/tools/ledgerman.py
ledgerman/tools/lm_convert.py