Metadata-Version: 1.1
Name: ledgerman
Version: 0.7.0
Summary: The python library for accounting and finance.
Home-page: http://github.com/finnmglas/LedgerMan
Author: Finn M Glas
Author-email: finn@finnmglas.com
License: MIT
Keywords: accounting finance manager money library ledger ledgerman crypto
Platform: UNKNOWN
Classifier: Development Status :: 3 - Alpha
Classifier: License :: OSI Approved :: MIT License
Classifier: Programming Language :: Python :: 3
Classifier: Intended Audience :: Financial and Insurance Industry
Classifier: Topic :: Office/Business :: Financial :: Accounting
